<?xml version="1.0" encoding="UTF-8"?>
<databaseChangeLog
    xmlns:xsi="http://www.w3.org/2001/XMLSchema-instance"
    xmlns="http://www.liquibase.org/xml/ns/dbchangelog"
    xsi:schemaLocation="http://www.liquibase.org/xml/ns/dbchangelog
        http://www.liquibase.org/xml/ns/dbchangelog/dbchangelog-4.23.xsd">

    <changeSet id="001-Healthcare-create-patients-table" author="Arivan.Amin">
        <createTable tableName="patients">
            <column name="id" type="Binary(16)" autoIncrement="true">
                <constraints primaryKey="true" nullable="false" />
            </column>
            <column name="firstName" type="VARCHAR(50)">
                <constraints nullable="false" />
            </column>
            <column name="firstName" type="VARCHAR(50)">
                <constraints nullable="false" />
            </column>
            <column name="email" type="VARCHAR(50)">
                <constraints unique="true" nullable="false" />
            </column>
            <column name="password" type="VARCHAR(255)" />
        </createTable>
    </changeSet>
</databaseChangeLog>
